muse/__init__.py
muse/cli.py
muse/client.py
muse/client_settings.py
muse/db.py
muse/device_manager.py
muse/exceptions.py
muse/scheduler.py
muse/server.py
muse/server_settings.py
muse/task.py
muse4ever-0.17.0.dist-info/METADATA
muse4ever-0.17.0.dist-info/WHEEL
muse4ever-0.17.0.dist-info/entry_points.txt
muse4ever-0.17.0.dist-info/licenses/LICENSE
muse4ever-0.17.0.dist-info/RECORD
