Metadata-Version: 2.1
Name: muse4ever
Version: 0.17.0
Summary: An ADB-powered framework for efficient Android command execution, device management, and job scheduling for developers and testers
Project-URL: Homepage, https://github.com/liuyibo/muse
Project-URL: Issues, https://github.com/liuyibo/muse/issues
Author-email: liuyibo <liuyibo1994@qq.com>, exzhawk <exzhawk@exz.me>
Maintainer-email: liuyibo <liuyibo1994@qq.com>
License-File: LICENSE
Keywords: adb,android,command-execution,development-tools,device-interaction,device-management,server-client
Classifier: Development Status :: 4 - Beta
Classifier: License :: OSI Approved :: MIT License
Classifier: Operating System :: OS Independent
Classifier: Programming Language :: Python :: 3
Requires-Python: >=3.6
Requires-Dist: humanize
Requires-Dist: loguru
Requires-Dist: requests
Requires-Dist: requests-toolbelt
Provides-Extra: server
Requires-Dist: flask; extra == 'server'
Requires-Dist: flask-cors; extra == 'server'
Requires-Dist: pymongo; extra == 'server'
